email_to_telegram/__init__.py
email_to_telegram/__main__.py
email_to_telegram/constants.py
email_to_telegram/email.py
email_to_telegram/telegram_bot.py
email_to_telegram/utils.py
test/__init__.py
test/fixture.py
test/test_util.py
email_to_telegram-1.1.2.dist-info/LICENSE
email_to_telegram-1.1.2.dist-info/METADATA
email_to_telegram-1.1.2.dist-info/WHEEL
email_to_telegram-1.1.2.dist-info/entry_points.txt
email_to_telegram-1.1.2.dist-info/top_level.txt
email_to_telegram-1.1.2.dist-info/RECORD
