Metadata-Version: 2.1
Name: email-to-telegram
Version: 1.1.2
Summary: Telegram bot that reads a mail file and forwards to Telegram chat
Home-page: https://github.com/ItsNotGoodName/email-to-telegram
Author: ItsNotGoodName
Author-email: gurnaindeol@gmail.com
License: UNKNOWN
Project-URL: Source, https://github.com/ItsNotGoodName/email-to-telegram
Keywords: bot,telegram
Platform: UNKNOWN
Requires-Python: >=3.6, <4
Requires-Dist: python-telegram-bot (<14.0,>=13.5)
Requires-Dist: watchdog (<3.0.0,>=2.1.1)
Requires-Dist: mail-parser (<4.0.0,>=3.15.0)
Provides-Extra: test
Requires-Dist: tox ; extra == 'test'
Requires-Dist: pytest ; extra == 'test'
Requires-Dist: pytest-datadir ; extra == 'test'
Requires-Dist: pytest-lazy-fixture ; extra == 'test'
